LICENSE
th2_common_utils/__init__.py
th2_common_utils/converters/filter_converters.py
th2_common_utils/converters/message_converters.py
th2_common_utils/event_components.py
th2_common_utils/event_utils.py
th2_common_utils/message_fields_access.py
th2_common_utils-2.2.0.dist-info/LICENSE
th2_common_utils-2.2.0.dist-info/METADATA
th2_common_utils-2.2.0.dist-info/WHEEL
th2_common_utils-2.2.0.dist-info/RECORD
